{
 "defis":[
        {
          "case":0,
          "defi":""
        },
        {
          "case":1,
          "defi":"Service"
        },
        {
          "case":2,
          "defi":"Echange à la diagonale"
        },
        {
          "case":3,
          "defi":"Match sur côté"
        },
        {
          "case":4,
          "defi":"Echange à la diagonale"
        },
        {
          "case":5,
          "defi":"Match à l'avant"
        },
        {
          "case":6,
          "defi":"Service"
        },
        {
          "case":7,
          "defi":"Match sur côté"
        },
        {
          "case":8,
          "defi":"Match à l'avant"
        },
        {
          "case":9,
          "defi":"Match tout terrain"
        },
        {
          "case":10,
          "defi":"Service"
        },
        {
          "case":11,
          "defi":"Echange à la diagonale"
        },
        {
          "case":12,
          "defi":"Match tout terrain"
        },
        {
          "case":13,
          "defi":"Match sur côté"
        },
        {
          "case":14,
          "defi":"Echange à la diagonale"
        },
        {
          "case":15,
          "defi":"Match à l'avant"
        },
        {
          "case":16,
          "defi":"Match sur côté"
        },
        {
          "case":17,
          "defi":"Service"
        },
        {
          "case":18,
          "defi":"Match sur côté"
        },
        {
          "case":19,
          "defi":"Match tout terrain"
        },
        {
          "case":21,
          "defi":"Match tout terrain"
        },
        {
          "case":22,
          "defi":"Match à l'avant"
        },
        {
          "case":23,
          "defi":"Match sur côté"
        },
        {
          "case":24,
          "defi":"Match tout terrain"
        },
        {
          "case":25,
          "defi":"Match à l'avant"
        },
        {
          "case":26,
          "defi":"Match tout terraine"
        },
        {
          "case":27,
          "defi":"Match tout terrain"
        },
        {
          "case":28,
          "defi":"Match tout terrain"
        },
        {
          "case":29,
          "defi":"Match à l'avant"
        },
        {
          "case":30,
          "defi":"Match à l'avant"
        },
        {
          "case":31,
          "defi":"Match tout terrain"
        },
        {
          "case":32,
          "defi":""
        }]
        
}